ontoaligner/VERSION
ontoaligner/__init__.py
ontoaligner/aligner/__init__.py
ontoaligner/aligner/fewshot/__init__.py
ontoaligner/aligner/fewshot/dataset.py
ontoaligner/aligner/fewshot/fewshot.py
ontoaligner/aligner/fewshot/models.py
ontoaligner/aligner/graph/__init__.py
ontoaligner/aligner/graph/graph.py
ontoaligner/aligner/graph/models.py
ontoaligner/aligner/icv/__init__.py
ontoaligner/aligner/icv/icv.py
ontoaligner/aligner/icv/models.py
ontoaligner/aligner/icv/tasks/__init__.py
ontoaligner/aligner/icv/tasks/base.py
ontoaligner/aligner/icv/tasks/demo.py
ontoaligner/aligner/icv/tasks/loader.py
ontoaligner/aligner/icv/utils/__init__.py
ontoaligner/aligner/icv/utils/context_manager.py
ontoaligner/aligner/icv/utils/forward_tracer.py
ontoaligner/aligner/icv/utils/llm_layers.py
ontoaligner/aligner/icv/utils/pca.py
ontoaligner/aligner/icv/utils/rng_ctx.py
ontoaligner/aligner/lightweight/__init__.py
ontoaligner/aligner/lightweight/lightweight.py
ontoaligner/aligner/lightweight/models.py
ontoaligner/aligner/llm/__init__.py
ontoaligner/aligner/llm/dataset.py
ontoaligner/aligner/llm/llm.py
ontoaligner/aligner/llm/models.py
ontoaligner/aligner/rag/__init__.py
ontoaligner/aligner/rag/dataset.py
ontoaligner/aligner/rag/models.py
ontoaligner/aligner/rag/rag.py
ontoaligner/aligner/retrieval/__init__.py
ontoaligner/aligner/retrieval/models.py
ontoaligner/aligner/retrieval/retrieval.py
ontoaligner/base/__init__.py
ontoaligner/base/dataset.py
ontoaligner/base/encoder.py
ontoaligner/base/model.py
ontoaligner/base/ontology.py
ontoaligner/encoder/__init__.py
ontoaligner/encoder/fewshot.py
ontoaligner/encoder/graph.py
ontoaligner/encoder/lightweight.py
ontoaligner/encoder/llm.py
ontoaligner/encoder/rag.py
ontoaligner/ontology/__init__.py
ontoaligner/ontology/generic.py
ontoaligner/ontology/oaei/__init__.py
ontoaligner/ontology/oaei/anatomy.py
ontoaligner/ontology/oaei/biodiv.py
ontoaligner/ontology/oaei/bioml.py
ontoaligner/ontology/oaei/commonkg.py
ontoaligner/ontology/oaei/food.py
ontoaligner-1.5.2.dist-info/METADATA
ontoaligner-1.5.2.dist-info/WHEEL
ontoaligner-1.5.2.dist-info/licenses/LICENSE
ontoaligner-1.5.2.dist-info/RECORD
