Metadata-Version: 2.4
Name: OntoAligner
Version: 1.5.2
Summary: OntoAligner: A Comprehensive Modular and Robust Python Toolkit for Ontology Alignment.
License: Apache-2.0
License-File: LICENSE
Author: Hamed Babaei Giglou
Author-email: hamedbabaeigiglou@gmail.com
Requires-Python: >=3.10,<3.14.0
Classifier: License :: OSI Approved :: Apache Software License
Classifier: Programming Language :: Python :: 3
Classifier: Programming Language :: Python :: 3.10
Classifier: Programming Language :: Python :: 3.11
Classifier: Programming Language :: Python :: 3.12
Classifier: Programming Language :: Python :: 3.13
Requires-Dist: argparse
Requires-Dist: bitsandbytes (>=0.45.1,<1.0.0) ; platform_system == "Linux"
Requires-Dist: datasets
Requires-Dist: huggingface-hub (>=0.34.4,<0.35.0)
Requires-Dist: numpy
Requires-Dist: openai (==1.56.0)
Requires-Dist: owlready2 (==0.44)
Requires-Dist: pandas
Requires-Dist: pathlib
Requires-Dist: pykeen (==1.11.1)
Requires-Dist: rank_bm25 (==0.2.2)
Requires-Dist: rapidfuzz (==3.5.2)
Requires-Dist: rdflib (==7.1.1)
Requires-Dist: scikit-learn
Requires-Dist: sentence-transformers (>=5.1.0,<6.0.0)
Requires-Dist: torch (>=2.8.0,<3.0.0)
Requires-Dist: tqdm
Requires-Dist: transformers (>=4.56.0,<5.0.0)
Project-URL: Homepage, https://ontoaligner.readthedocs.io/
Project-URL: Repository, https://github.com/sciknoworg/OntoAligner/
